mersenne_reducer.v
// Mersenne Reducer: Fast Modular Reduction for 2^p - 1
// NO division or modulo operators - pure bit manipulation!
//
// Algorithm: x mod (2^p - 1) = (x & mask) + (x >> p)
// Iterate until result < 2^p - 1
//
// Critical: This runs in O(1) hardware cycles vs software O(n) division

module mersenne_reducer #(
    parameter P = 13,           // Mersenne exponent (M_p = 2^P - 1)
    parameter WIDTH = 2*P       // Input width (enough for squared values)
)(
    input  wire clk,
    input  wire rst_n,
    input  wire valid_in,       // Start reduction
    input  wire [WIDTH-1:0] x,  // Input value
    output reg  [P-1:0] result, // Reduced result (< 2^P - 1)
    output reg  valid_out       // Output ready
);

    localparam MERSENNE = (1 << P) - 1;  // 2^P - 1

    // State machine for iterative reduction (Verilog-2005)
    localparam IDLE   = 2'b00;
    localparam REDUCE = 2'b01;
    localparam FINAL  = 2'b10;

    reg [1:0] state, next_state;

    reg [WIDTH-1:0] temp;       // Temporary accumulator
    reg [P-1:0] low, high_sum;
    reg [3:0] cycle_count;      // Reduction iterations

    // Combinational reduction logic (simplified for Verilog-2005)
    always @(*) begin
        low = temp[P-1:0];              // Lower P bits
        high_sum = temp[WIDTH-1:P];     // Upper bits (simplified)
    end

    // State transition
    always @(posedge clk or negedge rst_n) begin
        if (!rst_n) begin
            state <= IDLE;
            temp <= 0;
            result <= 0;
            valid_out <= 0;
            cycle_count <= 0;
        end else begin
            state <= next_state;
            valid_out <= 0;  // Default

            case (state)
                IDLE: begin
                    if (valid_in) begin
                        temp <= x;
                        cycle_count <= 0;
                    end
                end

                REDUCE: begin
                    temp <= low + high_sum;
                    cycle_count <= cycle_count + 1;
                end

                FINAL: begin
                    // Final adjustment: if result >= MERSENNE, subtract it
                    if ((low + high_sum) >= MERSENNE)
                        result <= (low + high_sum) - MERSENNE;
                    else
                        result <= low + high_sum;
                    valid_out <= 1;
                end
            endcase
        end
    end

    // Next state logic
    always @(*) begin
        next_state = state;
        case (state)
            IDLE:
                if (valid_in) next_state = REDUCE;

            REDUCE: begin
                // Check if we need more reduction (result still > P bits)
                if ((low + high_sum) < (1 << P))
                    next_state = FINAL;
                else if (cycle_count >= 4)  // Safety limit
                    next_state = FINAL;
                // else stay in REDUCE
            end

            FINAL:
                next_state = IDLE;
        endcase
    end

endmodule


// Fast single-cycle variant (combinational only, no FSM)
module mersenne_reducer_comb #(
    parameter P = 13,
    parameter WIDTH = 2*P
)(
    input  wire [WIDTH-1:0] x,
    output wire [P-1:0] result
);

    localparam MERSENNE = (1 << P) - 1;

    wire [P:0] stage1, stage2, stage3;

    // Stage 1: Split and add
    assign stage1 = x[P-1:0] + x[WIDTH-1:P];

    // Stage 2: Reduce if needed
    assign stage2 = (stage1 >= (1<<P)) ? (stage1[P-1:0] + stage1[P]) : stage1;

    // Stage 3: Final correction
    assign stage3 = (stage2 >= MERSENNE) ? (stage2 - MERSENNE) : stage2;

    assign result = stage3[P-1:0];

endmodule

lucas_lehmer_fsm.v
// Lucas-Lehmer Primality Test FSM
// Tests if M_p = 2^p - 1 is prime
//
// Algorithm:
//   s_0 = 4
//   s_i = (s_{i-1}^2 - 2) mod M_p  for i = 1 to p-2
//   M_p is prime iff s_{p-2} == 0
//
// Hardware Advantage: Uses bit-shift reduction instead of slow division!

module lucas_lehmer_fsm #(
    parameter P = 13                // Test M_13 = 2^13 - 1 = 8191
)(
    input  wire clk,
    input  wire rst_n,
    input  wire start,              // Begin primality test
    output reg  is_prime,           // Result: 1 if M_p is prime
    output reg  done,               // Test completed
    output reg  [15:0] cycles       // Clock cycles consumed
);

    localparam MERSENNE = (1 << P) - 1;
    localparam ITERATIONS = P - 2;

    localparam IDLE   = 3'b000;
    localparam INIT   = 3'b001;
    localparam SQUARE = 3'b010;
    localparam REDUCE = 3'b011;
    localparam CHECK  = 3'b100;
    localparam FINISH = 3'b101;

    reg [2:0] state;

    reg [P-1:0] s;                  // Current Lucas-Lehmer value
    reg [2*P-1:0] s_squared;        // s^2 (needs 2P bits)
    reg [2*P-1:0] s_squared_minus_2;
    reg [P-1:0] s_reduced;          // After modular reduction
    reg [15:0] iteration;

    // Mersenne reducer instance (combinational for speed)
    wire [P-1:0] reducer_out;
    mersenne_reducer_comb #(.P(P), .WIDTH(2*P)) reducer (
        .x(s_squared_minus_2),
        .result(reducer_out)
    );

    // FSM logic
    always @(posedge clk or negedge rst_n) begin
        if (!rst_n) begin
            state <= IDLE;
            s <= 0;
            iteration <= 0;
            is_prime <= 0;
            done <= 0;
            cycles <= 0;
        end else begin
            case (state)
                IDLE: begin
                    done <= 0;
                    cycles <= 0;
                    if (start) begin
                        state <= INIT;
                        iteration <= 0;
                        cycles <= cycles + 1;
                    end
                end

                INIT: begin
                    s <= 4;                     // s_0 = 4
                    state <= SQUARE;
                    cycles <= cycles + 1;
                end

                SQUARE: begin
                    s_squared <= s * s;         // Hardware multiplier
                    s_squared_minus_2 <= (s * s) - 2;  // Prepare for reducer
                    state <= REDUCE;
                    cycles <= cycles + 1;
                end

                REDUCE: begin
                    s_reduced <= reducer_out;   // Combinational reduction
                    s <= reducer_out;
                    state <= CHECK;
                    cycles <= cycles + 1;
                end

                CHECK: begin
                    iteration <= iteration + 1;
                    if (iteration >= ITERATIONS - 1) begin
                        state <= FINISH;
                    end else begin
                        state <= SQUARE;        // Next iteration
                    end
                    cycles <= cycles + 1;
                end

                FINISH: begin
                    is_prime <= (s == 0);       // Prime if s_{p-2} == 0
                    done <= 1;
                    state <= IDLE;
                    cycles <= cycles + 1;
                end

                default: state <= IDLE;
            endcase
        end
    end

endmodule


// Top-level wrapper with multiple exponent testing
module mersenne_prime_tester (
    input  wire clk,
    input  wire rst_n,
    input  wire start,
    input  wire [7:0] exponent,     // Which exponent to test
    output reg  is_prime,
    output reg  done,
    output reg  [15:0] cycles
);

    // Instantiate testers for common exponents
    wire done_13, done_17, done_19;
    wire prime_13, prime_17, prime_19;
    wire [15:0] cycles_13, cycles_17, cycles_19;

    lucas_lehmer_fsm #(.P(13)) test_13 (
        .clk(clk), .rst_n(rst_n),
        .start(start && exponent == 13),
        .is_prime(prime_13), .done(done_13), .cycles(cycles_13)
    );

    lucas_lehmer_fsm #(.P(17)) test_17 (
        .clk(clk), .rst_n(rst_n),
        .start(start && exponent == 17),
        .is_prime(prime_17), .done(done_17), .cycles(cycles_17)
    );

    lucas_lehmer_fsm #(.P(19)) test_19 (
        .clk(clk), .rst_n(rst_n),
        .start(start && exponent == 19),
        .is_prime(prime_19), .done(done_19), .cycles(cycles_19)
    );

    wire done_31, prime_31;
    wire [15:0] cycles_31;

    lucas_lehmer_fsm #(.P(31)) test_31 (
        .clk(clk), .rst_n(rst_n),
        .start(start && exponent == 31),
        .is_prime(prime_31), .done(done_31), .cycles(cycles_31)
    );

    // Multiplex outputs
    always @(*) begin
        case (exponent)
            13: begin
                is_prime = prime_13;
                done = done_13;
                cycles = cycles_13;
            end
            17: begin
                is_prime = prime_17;
                done = done_17;
                cycles = cycles_17;
            end
            19: begin
                is_prime = prime_19;
                done = done_19;
                cycles = cycles_19;
            end
            31: begin
                is_prime = prime_31;
                done = done_31;
                cycles = cycles_31;
            end
            default: begin
                is_prime = 0;
                done = 0;
                cycles = 0;
            end
        endcase
    end

endmodule

tb_mersenne.v
// Testbench for Mersenne Prime Hardware Tester
// Validates known Mersenne primes: M_13, M_17, M_19
// Reports clock cycles consumed (TPS = Throughput per Second)

`timescale 1ns/1ps

module tb_mersenne;

    reg clk;
    reg rst_n;
    reg start;
    reg [7:0] exponent;
    wire is_prime;
    wire done;
    wire [15:0] cycles;

    // Clock generation (100 MHz = 10ns period)
    initial begin
        clk = 0;
        forever #5 clk = ~clk;
    end

    // DUT instantiation
    mersenne_prime_tester dut (
        .clk(clk),
        .rst_n(rst_n),
        .start(start),
        .exponent(exponent),
        .is_prime(is_prime),
        .done(done),
        .cycles(cycles)
    );

    // Test vectors for known Mersenne primes (Verilog-2005 compatible)
    integer test_exponents [0:3];
    integer test_mersenne_values [0:3];
    integer test_expected [0:3];

    // Performance metrics
    real total_cycles;
    real total_time_ns;
    integer tests_passed;

    // Test sequence
    initial begin
        integer i;
        real start_time, end_time, duration_ns;
        integer test_p, test_mersenne, test_expected_prime;

        // Initialize test data
        test_exponents[0] = 13; test_mersenne_values[0] = 8191;         test_expected[0] = 1;
        test_exponents[1] = 17; test_mersenne_values[1] = 131071;       test_expected[1] = 1;
        test_exponents[2] = 19; test_mersenne_values[2] = 524287;       test_expected[2] = 1;
        test_exponents[3] = 31; test_mersenne_values[3] = 2147483647;   test_expected[3] = 1;

        total_cycles = 0;
        total_time_ns = 0;
        tests_passed = 0;

        $display("========================================");
        $display("Mersenne Prime Hardware Tester");
        $display("Testing bit-shift reduction vs CPU division");
        $display("========================================\n");

        // Reset
        rst_n = 0;
        start = 0;
        exponent = 0;
        #20;
        rst_n = 1;
        #10;

        // Run tests for each exponent
        for (i = 0; i < 4; i = i + 1) begin
            test_p = test_exponents[i];
            test_mersenne = test_mersenne_values[i];
            test_expected_prime = test_expected[i];

            $display("[TEST %0d] Testing M_%0d = 2^%0d - 1 = %0d",
                     i+1, test_p, test_p, test_mersenne);

            exponent = test_p;
            start_time = $realtime;

            // Pulse start signal
            @(posedge clk);
            start = 1;
            @(posedge clk);
            start = 0;

            // Wait for completion
            wait(done == 1);
            @(posedge clk);
            end_time = $realtime;

            duration_ns = end_time - start_time;
            total_cycles = total_cycles + cycles;
            total_time_ns = total_time_ns + duration_ns;

            // Verify result
            if (is_prime == test_expected_prime) begin
                tests_passed = tests_passed + 1;
                $display("  PASS: is_prime = %0b (expected %0b)",
                         is_prime, test_expected_prime);
            end else begin
                $display("  FAIL: is_prime = %0b (expected %0b)",
                         is_prime, test_expected_prime);
            end

            $display("  Clock Cycles: %0d", cycles);
            $display("  Time: %.2f ns", duration_ns);
            $display("  Throughput: %.2f cycles/ns\n", cycles / duration_ns);

            #50;  // Gap between tests
        end

        // Summary
        $display("========================================");
        $display("SUMMARY");
        $display("========================================");
        $display("Tests Passed: %0d / 4", tests_passed);
        $display("Total Cycles: %.0f", total_cycles);
        $display("Total Time: %.2f ns (%.2f us)", total_time_ns, total_time_ns/1000);
        $display("Average Throughput: %.2f cycles/ns", total_cycles / total_time_ns);
        $display("\n========================================");
        $display("HARDWARE ADVANTAGE");
        $display("========================================");
        $display("- NO division operators (/) used");
        $display("- NO modulo operators (%%) used");
        $display("- Pure bit-shift & addition logic");
        $display("- Single-cycle modular reduction");
        $display("========================================\n");

        if (tests_passed == 4)
            $display("ALL TESTS PASSED! Hardware is correct.\n");
        else
            $display("SOME TESTS FAILED!\n");

        $finish;
    end

    // Timeout watchdog (prevent infinite simulation)
    initial begin
        #1000000;  // 1ms timeout
        $display("\n⚠️  TIMEOUT: Simulation exceeded 1ms");
        $finish;
    end

    // Waveform dump for debugging
    initial begin
        $dumpfile("mersenne_prime.vcd");
        $dumpvars(0, tb_mersenne);
    end

endmodule


// Standalone reducer testbench (unit test)
module tb_reducer;
    reg clk, rst_n;
    reg [25:0] x;
    wire [12:0] result;

    mersenne_reducer_comb #(.P(13), .WIDTH(26)) dut (
        .x(x),
        .result(result)
    );

    initial begin
        clk = 0;
        forever #5 clk = ~clk;
    end

    initial begin
        $display("Testing Mersenne Reducer (M_13 = 8191)");

        // Test case 1: 100 mod 8191 = 100
        x = 100;
        #1;
        $display("x=%0d, result=%0d (expected %0d)", x, result, 100);

        // Test case 2: 8191 mod 8191 = 0
        x = 8191;
        #1;
        $display("x=%0d, result=%0d (expected %0d)", x, result, 0);

        // Test case 3: 16382 mod 8191 = 0 (2 * M_13)
        x = 16382;
        #1;
        $display("x=%0d, result=%0d (expected %0d)", x, result, 0);

        // Test case 4: 16 * 16 = 256
        x = 16 * 16;
        #1;
        $display("x=%0d, result=%0d (expected %0d)", x, result, 256);

        $finish;
    end
endmodule

mersenne_prime.vcd
$date
	Thu Feb 12 16:04:09 2026
$end
$version
	Icarus Verilog
$end
$timescale
	1ps
$end
$scope module tb_mersenne $end
$var wire 1 ! is_prime $end
$var wire 1 " done $end
$var wire 16 # cycles [15:0] $end
$var reg 1 $ clk $end
$var reg 8 % exponent [7:0] $end
$var reg 1 & rst_n $end
$var reg 1 ' start $end
$var integer 32 ( tests_passed [31:0] $end
$var real 1 ) total_cycles $end
$var real 1 * total_time_ns $end
$scope module dut $end
$var wire 1 $ clk $end
$var wire 8 + exponent [7:0] $end
$var wire 1 & rst_n $end
$var wire 1 ' start $end
$var wire 1 , prime_31 $end
$var wire 1 - prime_19 $end
$var wire 1 . prime_17 $end
$var wire 1 / prime_13 $end
$var wire 1 0 done_31 $end
$var wire 1 1 done_19 $end
$var wire 1 2 done_17 $end
$var wire 1 3 done_13 $end
$var wire 16 4 cycles_31 [15:0] $end
$var wire 16 5 cycles_19 [15:0] $end
$var wire 16 6 cycles_17 [15:0] $end
$var wire 16 7 cycles_13 [15:0] $end
$var reg 16 8 cycles [15:0] $end
$var reg 1 " done $end
$var reg 1 ! is_prime $end
$scope module test_13 $end
$var wire 1 $ clk $end
$var wire 1 & rst_n $end
$var wire 1 9 start $end
$var wire 13 : reducer_out [12:0] $end
$var reg 16 ; cycles [15:0] $end
$var reg 1 3 done $end
$var reg 1 / is_prime $end
$var reg 16 < iteration [15:0] $end
$var reg 13 = s [12:0] $end
$var reg 13 > s_reduced [12:0] $end
$var reg 26 ? s_squared [25:0] $end
$var reg 26 @ s_squared_minus_2 [25:0] $end
$var reg 3 A state [2:0] $end
$scope module reducer $end
$var wire 26 B x [25:0] $end
$var wire 14 C stage3 [13:0] $end
$var wire 14 D stage2 [13:0] $end
$var wire 14 E stage1 [13:0] $end
$var wire 13 F result [12:0] $end
$upscope $end
$upscope $end
$scope module test_17 $end
$var wire 1 $ clk $end
$var wire 1 & rst_n $end
$var wire 1 G start $end
$var wire 17 H reducer_out [16:0] $end
$var reg 16 I cycles [15:0] $end
$var reg 1 2 done $end
$var reg 1 . is_prime $end
$var reg 16 J iteration [15:0] $end
$var reg 17 K s [16:0] $end
$var reg 17 L s_reduced [16:0] $end
$var reg 34 M s_squared [33:0] $end
$var reg 34 N s_squared_minus_2 [33:0] $end
$var reg 3 O state [2:0] $end
$scope module reducer $end
$var wire 34 P x [33:0] $end
$var wire 18 Q stage3 [17:0] $end
$var wire 18 R stage2 [17:0] $end
$var wire 18 S stage1 [17:0] $end
$var wire 17 T result [16:0] $end
$upscope $end
$upscope $end
$scope module test_19 $end
$var wire 1 $ clk $end
$var wire 1 & rst_n $end
$var wire 1 U start $end
$var wire 19 V reducer_out [18:0] $end
$var reg 16 W cycles [15:0] $end
$var reg 1 1 done $end
$var reg 1 - is_prime $end
$var reg 16 X iteration [15:0] $end
$var reg 19 Y s [18:0] $end
$var reg 19 Z s_reduced [18:0] $end
$var reg 38 [ s_squared [37:0] $end
$var reg 38 \ s_squared_minus_2 [37:0] $end
$var reg 3 ] state [2:0] $end
$scope module reducer $end
$var wire 38 ^ x [37:0] $end
$var wire 20 _ stage3 [19:0] $end
$var wire 20 ` stage2 [19:0] $end
$var wire 20 a stage1 [19:0] $end
$var wire 19 b result [18:0] $end
$upscope $end
$upscope $end
$scope module test_31 $end
$var wire 1 $ clk $end
$var wire 1 & rst_n $end
$var wire 1 c start $end
$var wire 31 d reducer_out [30:0] $end
$var reg 16 e cycles [15:0] $end
$var reg 1 0 done $end
$var reg 1 , is_prime $end
$var reg 16 f iteration [15:0] $end
$var reg 31 g s [30:0] $end
$var reg 31 h s_reduced [30:0] $end
$var reg 62 i s_squared [61:0] $end
$var reg 62 j s_squared_minus_2 [61:0] $end
$var reg 3 k state [2:0] $end
$scope module reducer $end
$var wire 62 l x [61:0] $end
$var wire 32 m stage3 [31:0] $end
$var wire 32 n stage2 [31:0] $end
$var wire 32 o stage1 [31:0] $end
$var wire 31 p result [30:0] $end
$upscope $end
$upscope $end
$upscope $end
$scope begin $unm_blk_30 $end
$var real 1 q duration_ns $end
$var real 1 r end_time $end
$var integer 32 s i [31:0] $end
$var real 1 t start_time $end
$var integer 32 u test_expected_prime [31:0] $end
$var integer 32 v test_mersenne [31:0] $end
$var integer 32 w test_p [31:0] $end
$upscope $end
$upscope $end
$enddefinitions $end
#0
$dumpvars
bx w
bx v
bx u
r0 t
bx s
r0 r
r0 q
bx p
bx o
bx n
bx m
bx l
b0 k
bx j
bx i
bx h
b0 g
b0 f
b0 e
bx d
0c
bx b
bx a
bx `
bx _
bx ^
b0 ]
bx \
bx [
bx Z
b0 Y
b0 X
b0 W
bx V
0U
bx T
bx S
bx R
bx Q
bx P
b0 O
bx N
bx M
bx L
b0 K
b0 J
b0 I
bx H
0G
bx F
bx E
bx D
bx C
bx B
b0 A
bx @
bx ?
bx >
b0 =
b0 <
b0 ;
bx :
09
b0 8
b0 7
b0 6
b0 5
b0 4
03
02
01
00
0/
0.
0-
0,
b0 +
r0 *
r0 )
b0 (
0'
0&
b0 %
0$
b0 #
0"
0!
$end
#5000
1$
#10000
0$
#15000
1$
#20000
0$
1&
#25000
1$
#30000
0$
r30 t
b1101 %
b1101 +
b1 u
b1111111111111 v
b1101 w
b0 s
#35000
19
1'
1$
#40000
0$
#45000
b1 #
b1 8
b1 7
b1 ;
b1 A
09
0'
1$
#50000
0$
#55000
b10 #
b10 8
b10 7
b10 ;
b10 A
b100 =
1$
#60000
0$
#65000
b1110 :
b1110 F
b1110 C
b1110 D
b11 #
b11 8
b1110 E
b11 7
b11 ;
b11 A
b1110 @
b1110 B
b10000 ?
1$
#70000
0$
#75000
b100 #
b100 8
b100 7
b100 ;
b100 A
b1110 =
b1110 >
1$
#80000
0$
#85000
b101 #
b101 8
b101 7
b101 ;
b10 A
b1 <
1$
#90000
0$
#95000
b11000010 :
b11000010 F
b11000010 C
b11000010 D
b110 #
b110 8
b11000010 E
b110 7
b110 ;
b11 A
b11000010 @
b11000010 B
b11000100 ?
1$
#100000
0$
#105000
b111 #
b111 8
b111 7
b111 ;
b100 A
b11000010 =
b11000010 >
1$
#110000
0$
#115000
b1000 #
b1000 8
b1000 7
b1000 ;
b10 A
b10 <
1$
#120000
0$
#125000
b1001100000110 :
b1001100000110 F
b1001100000110 C
b1001100000110 D
b1001 #
b1001 8
b1001100000110 E
b1001 7
b1001 ;
b11 A
b1001001100000010 @
b1001001100000010 B
b1001001100000100 ?
1$
#130000
0$
#135000
b1010 #
b1010 8
b1010 7
b1010 ;
b100 A
b1001100000110 =
b1001100000110 >
1$
#140000
0$
#145000
b1011 #
b1011 8
b1011 7
b1011 ;
b10 A
b11 <
1$
#150000
0$
#155000
b111101110001 :
b111101110001 F
b111101110001 C
b111101110001 D
b1100 #
b1100 8
b111101110001 E
b1100 7
b1100 ;
b11 A
b1011010011110010000100010 @
b1011010011110010000100010 B
b1011010011110010000100100 ?
1$
#160000
0$
#165000
b1101 #
b1101 8
b1101 7
b1101 ;
b100 A
b111101110001 =
b111101110001 >
1$
#170000
0$
#175000
b1110 #
b1110 8
b1110 7
b1110 ;
b10 A
b100 <
1$
#180000
0$
#185000
b1011101010010 :
b1011101010010 F
b1011101010010 C
b1011101010010 D
b1111 #
b1111 8
b1011101010010 E
b1111 7
b1111 ;
b11 A
b111011100110111111011111 @
b111011100110111111011111 B
b111011100110111111100001 ?
1$
#190000
0$
#195000
b10000 #
b10000 8
b10000 7
b10000 ;
b100 A
b1011101010010 =
b1011101010010 >
1$
#200000
0$
#205000
b10001 #
b10001 8
b10001 7
b10001 ;
b10 A
b101 <
1$
#210000
0$
#215000
b11101000001 :
b11101000001 F
b11101000001 C
b11101000001 D
b10010 #
b10010 8
b10011101000000 E
b10010 7
b10010 ;
b11 A
b10000111111101011001000010 @
b10000111111101011001000010 B
b10000111111101011001000100 ?
1$
#220000
0$
#225000
b10011 #
b10011 8
b10011 7
b10011 ;
b100 A
b11101000001 =
b11101000001 >
1$
#230000
0$
#235000
b10100 #
b10100 8
b10100 7
b10100 ;
b10 A
b110 <
1$
#240000
0$
#245000
b100100 :
b100100 F
b100100 C
b100100 D
b10101 #
b10101 8
b10000000100011 E
b10101 7
b10101 ;
b11 A
b1101001001111001111111 @
b1101001001111001111111 B
b1101001001111010000001 ?
1$
#250000
0$
#255000
b10110 #
b10110 8
b10110 7
b10110 ;
b100 A
b100100 =
b100100 >
1$
#260000
0$
#265000
b10111 #
b10111 8
b10111 7
b10111 ;
b10 A
b111 <
1$
#270000
0$
#275000
b10100001110 :
b10100001110 F
b10100001110 C
b10100001110 D
b11000 #
b11000 8
b10100001110 E
b11000 7
b11000 ;
b11 A
b10100001110 @
b10100001110 B
b10100010000 ?
1$
#280000
0$
#285000
b11001 #
b11001 8
b11001 7
b11001 ;
b100 A
b10100001110 =
b10100001110 >
1$
#290000
0$
#295000
b11010 #
b11010 8
b11010 7
b11010 ;
b10 A
b1000 <
1$
#300000
0$
#305000
b110110001110 :
b110110001110 F
b110110001110 C
b110110001110 D
b11011 #
b11011 8
b110110001110 E
b11011 7
b11011 ;
b11 A
b110011000110011000010 @
b110011000110011000010 B
b110011000110011000100 ?
1$
#310000
0$
#315000
b11100 #
b11100 8
b11100 7
b11100 ;
b100 A
b110110001110 =
b110110001110 >
1$
#320000
0$
#325000
b11101 #
b11101 8
b11101 7
b11101 ;
b10 A
b1001 <
1$
#330000
0$
#335000
b10000000 :
b10000000 F
b10000000 C
b10000000 D
b11110 #
b11110 8
b10000001111111 E
b11110 7
b11110 ;
b11 A
b101101111011101011000010 @
b101101111011101011000010 B
b101101111011101011000100 ?
1$
#340000
0$
#345000
b11111 #
b11111 8
b11111 7
b11111 ;
b100 A
b10000000 =
b10000000 >
1$
#350000
0$
#355000
b100000 #
b100000 8
b100000 7
b100000 ;
b10 A
b1010 <
1$
#360000
0$
#365000
b0 :
b0 F
b0 C
b1111111111111 D
b100001 #
b100001 8
b1111111111111 E
b100001 7
b100001 ;
b11 A
b11111111111110 @
b11111111111110 B
b100000000000000 ?
1$
#370000
0$
#375000
b100010 #
b100010 8
b100010 7
b100010 ;
b100 A
b0 =
b0 >
1$
#380000
0$
#385000
b100011 #
b100011 8
b100011 7
b100011 ;
b101 A
b1011 <
1$
#390000
0$
#395000
b100100 #
b100100 8
1"
1!
b100100 7
b100100 ;
b0 A
13
1/
1$
#400000
0$
#405000
b0 #
b0 8
0"
b0 7
b0 ;
03
b1 (
r375 *
r36 )
r375 q
r405 r
1$
#410000
0$
#415000
1$
#420000
0$
#425000
1$
#430000
0$
#435000
1$
#440000
0$
#445000
1$
#450000
0$
#455000
1G
1'
0!
1$
r455 t
b10001 %
b10001 +
b11111111111111111 v
b10001 w
b1 s
#460000
0$
#465000
b1 #
b1 8
b1 6
b1 I
b1 O
0G
0'
1$
#470000
0$
#475000
b10 #
b10 8
b10 6
b10 I
b10 O
b100 K
1$
#480000
0$
#485000
b1110 H
b1110 T
b1110 Q
b1110 R
b11 #
b11 8
b1110 S
b11 6
b11 I
b11 O
b1110 N
b1110 P
b10000 M
1$
#490000
0$
#495000
b100 #
b100 8
b100 6
b100 I
b100 O
b1110 K
b1110 L
1$
#500000
0$
#505000
b101 #
b101 8
b101 6
b101 I
b10 O
b1 J
1$
#510000
0$
#515000
b11000010 H
b11000010 T
b11000010 Q
b11000010 R
b110 #
b110 8
b11000010 S
b110 6
b110 I
b11 O
b11000010 N
b11000010 P
b11000100 M
1$
#520000
0$
#525000
b111 #
b111 8
b111 6
b111 I
b100 O
b11000010 K
b11000010 L
1$
#530000
0$
#535000
b1000 #
b1000 8
b1000 6
b1000 I
b10 O
b10 J
1$
#540000
0$
#545000
b1001001100000010 H
b1001001100000010 T
b1001001100000010 Q
b1001001100000010 R
b1001 #
b1001 8
b1001001100000010 S
b1001 6
b1001 I
b11 O
b1001001100000010 N
b1001001100000010 P
b1001001100000100 M
1$
#550000
0$
#555000
b1010 #
b1010 8
b1010 6
b1010 I
b100 O
b1001001100000010 K
b1001001100000010 L
1$
#560000
0$
#565000
b1011 #
b1011 8
b1011 6
b1011 I
b10 O
b11 J
1$
#570000
0$
#575000
b10111011000110111 H
b10111011000110111 T
b10111011000110111 Q
b10111011000110111 R
b1100 #
b1100 8
b10111011000110111 S
b1100 6
b1100 I
b11 O
b1010100011010110100110000000010 N
b1010100011010110100110000000010 P
b1010100011010110100110000000100 M
1$
#580000
0$
#585000
b1101 #
b1101 8
b1101 6
b1101 I
b100 O
b10111011000110111 K
b10111011000110111 L
1$
#590000
0$
#595000
b1110 #
b1110 8
b1110 6
b1110 I
b10 O
b100 J
1$
#600000
0$
#605000
b11101000101010001 H
b11101000101010001 T
b11101000101010001 Q
b11101000101010001 R
b1111 #
b1111 8
b11101000101010001 S
b1111 6
b1111 I
b11 O
b1000100011000001001011111111001111 N
b1000100011000001001011111111001111 P
b1000100011000001001011111111010001 M
1$
#610000
0$
#615000
b10000 #
b10000 8
b10000 6
b10000 I
b100 O
b11101000101010001 K
b11101000101010001 L
1$
#620000
0$
#625000
b10001 #
b10001 8
b10001 6
b10001 I
b10 O
b101 J
1$
#630000
0$
#635000
b10000001010000011 H
b10000001010000011 T
b10000001010000011 Q
b10000001010000011 R
b10010 #
b10010 8
b110000001010000010 S
b10010 6
b10010 I
b11 O
b1101001101110001110101101110011111 N
b1101001101110001110101101110011111 P
b1101001101110001110101101110100001 M
1$
#640000
0$
#645000
b10011 #
b10011 8
b10011 6
b10011 I
b100 O
b10000001010000011 K
b10000001010000011 L
1$
#650000
0$
#655000
b10100 #
b10100 8
b10100 6
b10100 I
b10 O
b110 J
1$
#660000
0$
#665000
b1101000110001101 H
b1101000110001101 T
b1101000110001101 Q
b1101000110001101 R
b10101 #
b10101 8
b1101000110001101 S
b10101 6
b10101 I
b11 O
b100000101000011000100111100000111 N
b100000101000011000100111100000111 P
b100000101000011000100111100001001 M
1$
#670000
0$
#675000
b10110 #
b10110 8
b10110 6
b10110 I
b100 O
b1101000110001101 K
b1101000110001101 L
1$
#680000
0$
#685000
b10111 #
b10111 8
b10111 6
b10111 I
b10 O
b111 J
1$
#690000
0$
#695000
b11101110101101010 H
b11101110101101010 T
b11101110101101010 Q
b11101110101101010 R
b11000 #
b11000 8
b11101110101101010 S
b11000 6
b11000 I
b11 O
b10101011100001111000011110100111 N
b10101011100001111000011110100111 P
b10101011100001111000011110101001 M
1$
#700000
0$
#705000
b11001 #
b11001 8
b11001 6
b11001 I
b100 O
b11101110101101010 K
b11101110101101010 L
1$
#710000
0$
#715000
b11010 #
b11010 8
b11010 6
b11010 I
b10 O
b1000 J
1$
#720000
0$
#725000
b11110110100001100 H
b11110110100001100 T
b11110110100001100 Q
b11110110100001100 R
b11011 #
b11011 8
b11110110100001100 S
b11011 6
b11011 I
b11 O
b1101111010010101000010111111100010 N
b1101111010010101000010111111100010 P
b1101111010010101000010111111100100 M
1$
#730000
0$
#735000
b11100 #
b11100 8
b11100 6
b11100 I
b100 O
b11110110100001100 K
b11110110100001100 L
1$
#740000
0$
#745000
b11101 #
b11101 8
b11101 6
b11101 I
b10 O
b1001 J
1$
#750000
0$
#755000
b10001001101011010 H
b10001001101011010 T
b10001001101011010 Q
b10001001101011010 R
b11110 #
b11110 8
b110001001101011001 S
b11110 6
b11110 I
b11 O
b1110110101100101110011100010001110 N
b1110110101100101110011100010001110 P
b1110110101100101110011100010010000 M
1$
#760000
0$
#765000
b11111 #
b11111 8
b11111 6
b11111 I
b100 O
b10001001101011010 K
b10001001101011010 L
1$
#770000
0$
#775000
b100000 #
b100000 8
b100000 6
b100000 I
b10 O
b1010 J
1$
#780000
0$
#785000
b10000111110110111 H
b10000111110110111 T
b10000111110110111 Q
b10000111110110111 R
b100001 #
b100001 8
b10000111110110111 S
b100001 6
b100001 I
b11 O
b100101000001010100111101110100010 N
b100101000001010100111101110100010 P
b100101000001010100111101110100100 M
1$
#790000
0$
#795000
b100010 #
b100010 8
b100010 6
b100010 I
b100 O
b10000111110110111 K
b10000111110110111 L
1$
#800000
0$
#805000
b100011 #
b100011 8
b100011 6
b100011 I
b10 O
b1011 J
1$
#810000
0$
#815000
b11000010100000001 H
b11000010100000001 T
b11000010100000001 Q
b11000010100000001 R
b100100 #
b100100 8
b11000010100000001 S
b100100 6
b100100 I
b11 O
b100100000011001001111010011001111 N
b100100000011001001111010011001111 P
b100100000011001001111010011010001 M
1$
#820000
0$
#825000
b100101 #
b100101 8
b100101 6
b100101 I
b100 O
b11000010100000001 K
b11000010100000001 L
1$
#830000
0$
#835000
b100110 #
b100110 8
b100110 6
b100110 I
b10 O
b1100 J
1$
#840000
0$
#845000
b10011000110001101 H
b10011000110001101 T
b10011000110001101 Q
b10011000110001101 R
b100111 #
b100111 8
b10011000110001101 S
b100111 6
b100111 I
b11 O
b1001001111000111000000100111111111 N
b1001001111000111000000100111111111 P
b1001001111000111000000101000000001 M
1$
#850000
0$
#855000
b101000 #
b101000 8
b101000 6
b101000 I
b100 O
b10011000110001101 K
b10011000110001101 L
1$
#860000
0$
#865000
b101001 #
b101001 8
b101001 6
b101001 I
b10 O
b1101 J
1$
#870000
0$
#875000
b11111110111111111 H
b11111110111111111 T
b11111110111111111 Q
b11111110111111111 R
b101010 #
b101010 8
b11111110111111111 S
b101010 6
b101010 I
b11 O
b101101100101100010100011110100111 N
b101101100101100010100011110100111 P
b101101100101100010100011110101001 M
1$
#880000
0$
#885000
b101011 #
b101011 8
b101011 6
b101011 I
b100 O
b11111110111111111 K
b11111110111111111 L
1$
#890000
0$
#895000
b101100 #
b101100 8
b101100 6
b101100 I
b10 O
b1110 J
1$
#900000
0$
